Metadata-Version: 1.1
Name: tooldog
Version: 0.3.5
Summary: Tool description generator (from https//bio.tools to XML and CWL)
Home-page: UNKNOWN
Author: Kenzo-Hugo Hillion, Ivan Kuzmin and Herve Menager
Author-email: kehillio@pasteur.fr
License: MIT
Keywords: biotools,galaxy,xml,cwl
Platform: UNKNOWN
Classifier: Development Status :: 4 - Beta
Classifier: Topic :: Scientific/Engineering :: Bio-Informatics
Classifier: Operating System :: OS Independent
Classifier: Intended Audience :: Developers
Classifier: Intended Audience :: Science/Research
Classifier: Environment :: Console
